CHANGELOG.md
MANIFEST.in
README.md
setup.cfg
setup.py
versioneer.py
src/libreflow/__init__.py
src/libreflow.extensions.sk.tvpaint_scene_builder.egg-info/PKG-INFO
src/libreflow.extensions.sk.tvpaint_scene_builder.egg-info/SOURCES.txt
src/libreflow.extensions.sk.tvpaint_scene_builder.egg-info/dependency_links.txt
src/libreflow.extensions.sk.tvpaint_scene_builder.egg-info/top_level.txt
src/libreflow/extensions/__init__.py
src/libreflow/extensions/sk/__init__.py
src/libreflow/extensions/sk/tvpaint_scene_builder/__init__.py
src/libreflow/extensions/sk/tvpaint_scene_builder/_version.py
src/libreflow/extensions/sk/tvpaint_scene_builder/scripts/__init__.py
src/libreflow/extensions/sk/tvpaint_scene_builder/scripts/clean_up.py
src/libreflow/extensions/sk/tvpaint_scene_builder/scripts/import_layers.py
src/libreflow/extensions/sk/tvpaint_scene_builder/scripts/reload_audio.py
src/libreflow/extensions/sk/tvpaint_scene_builder/scripts/update_layers.py